{
  "domain": "kaitchup.substack.com",
  "timestamp": "20250916_133614",
  "quality_report": {
    "total_paths": 146,
    "paths_meeting_golden_image": 145,
    "total_phrases_generated": 3501,
    "average_quality_score": 0.9965753424657534
  },
  "domain_analysis": {
    "domain_type": "technology",
    "key_entities": [
      "Kaitchup",
      "Substack",
      "Tutorials",
      "Notebooks",
      "The Kaitchup Index"
    ],
    "terminology_style": "technical",
    "user_goals": [
      "access tutorials and guides",
      "read articles and notes",
      "explore the Kaitchup Index",
      "stay updated with the Weekly Kaitchup",
      "learn about the author and their work"
    ]
  },
  "golden_image_type": "technology"
}